odoo8_addon_l10n_es_vat_book-8.0.1.0.1-py3.6-nspkg.pth
odoo_addons/l10n_es_vat_book/README.rst
odoo_addons/l10n_es_vat_book/__init__.py
odoo_addons/l10n_es_vat_book/__openerp__.py
odoo_addons/l10n_es_vat_book/data/map_taxes_vat_book.xml
odoo_addons/l10n_es_vat_book/i18n/ca.po
odoo_addons/l10n_es_vat_book/i18n/es.po
odoo_addons/l10n_es_vat_book/i18n/l10n_es_vat_book.pot
odoo_addons/l10n_es_vat_book/models/__init__.py
odoo_addons/l10n_es_vat_book/models/l10n_es_vat_book.py
odoo_addons/l10n_es_vat_book/models/l10n_es_vat_book_invoice_tax_lines.py
odoo_addons/l10n_es_vat_book/models/l10n_es_vat_book_issued_lines.py
odoo_addons/l10n_es_vat_book/models/l10n_es_vat_book_issued_tax_summary.py
odoo_addons/l10n_es_vat_book/models/l10n_es_vat_book_received_lines.py
odoo_addons/l10n_es_vat_book/models/l10n_es_vat_book_received_tax_summary.py
odoo_addons/l10n_es_vat_book/models/l10n_es_vat_book_rectification_issued_lines.py
odoo_addons/l10n_es_vat_book/models/l10n_es_vat_book_rectification_issued_tax_summary.py
odoo_addons/l10n_es_vat_book/models/l10n_es_vat_book_rectification_received_lines.py
odoo_addons/l10n_es_vat_book/models/l10n_es_vat_book_rectification_received_tax_summary.py
odoo_addons/l10n_es_vat_book/report/__init__.py
odoo_addons/l10n_es_vat_book/report/report_paper_format.xml
odoo_addons/l10n_es_vat_book/report/report_views.xml
odoo_addons/l10n_es_vat_book/report/vat_book_invoices_issued.py
odoo_addons/l10n_es_vat_book/report/vat_book_invoices_issued.xml
odoo_addons/l10n_es_vat_book/report/vat_book_invoices_received.py
odoo_addons/l10n_es_vat_book/report/vat_book_invoices_received.xml
odoo_addons/l10n_es_vat_book/report/vat_book_rectification_issued_invoices.py
odoo_addons/l10n_es_vat_book/report/vat_book_rectification_issued_invoices.xml
odoo_addons/l10n_es_vat_book/report/vat_book_rectification_received_invoices.py
odoo_addons/l10n_es_vat_book/report/vat_book_rectification_received_invoices.xml
odoo_addons/l10n_es_vat_book/security/ir.model.access.csv
odoo8_addon_l10n_es_vat_book-8.0.1.0.1.dist-info/METADATA
odoo8_addon_l10n_es_vat_book-8.0.1.0.1.dist-info/WHEEL
odoo8_addon_l10n_es_vat_book-8.0.1.0.1.dist-info/namespace_packages.txt
odoo8_addon_l10n_es_vat_book-8.0.1.0.1.dist-info/top_level.txt
odoo8_addon_l10n_es_vat_book-8.0.1.0.1.dist-info/RECORD
