Metadata-Version: 2.1
Name: odoo8-addon-l10n-es-vat-book
Version: 8.0.1.0.1
Summary: Libro de IVA
Home-page: http://www.praxya.com
Author: PRAXYA, Odoo Community Association (OCA)
Author-email: support@odoo-community.org
License: AGPL-3
Platform: UNKNOWN
Classifier: Programming Language :: Python
Classifier: Framework :: Odoo
Classifier: License :: OSI Approved :: GNU Affero General Public License v3
Requires-Python: ~=2.7
Requires-Dist: odoo8-addon-account-invoice-currency
Requires-Dist: odoo8-addon-account-refund-original
Requires-Dist: odoo8-addon-l10n-es-aeat
Requires-Dist: odoo (<9.0a,>=8.0a)
